dbx_auth_helper/__init__.py
dbx_auth_helper/access.py
dbx_auth_helper/auth.py
dbx_auth_helper-0.1.0.dist-info/LICENSE
dbx_auth_helper-0.1.0.dist-info/METADATA
dbx_auth_helper-0.1.0.dist-info/WHEEL
dbx_auth_helper-0.1.0.dist-info/top_level.txt
dbx_auth_helper-0.1.0.dist-info/RECORD
