Metadata-Version: 2.1
Name: dbx-auth-helper
Version: 0.1.0
Summary: Dropbox authentication and refresh/access code helper.
Home-page: https://github.com/Ceiling-Fan-Studios/Dropbox-Authentication-Helper
Author: Micah Crandell
Author-email: micah1crandell@gmail.com
License: UNKNOWN
Platform: UNKNOWN
Classifier: Development Status :: 4 - Beta
Classifier: Intended Audience :: Developers
Classifier: License :: OSI Approved :: MIT License
Classifier: Programming Language :: Python :: 3
License-File: LICENSE
